buscoplotpy/__init__.py
buscoplotpy/graphics/__init__.py
buscoplotpy/graphics/chromosome.py
buscoplotpy/graphics/karyoplot.py
buscoplotpy/graphics/label.py
buscoplotpy/graphics/organism_busco_barplot.py
buscoplotpy/utils/__init__.py
buscoplotpy/utils/load_busco_fulltable.py
buscoplotpy/utils/load_json_summary.py
buscoplotpy-0.0.2.dist-info/LICENSE
buscoplotpy-0.0.2.dist-info/METADATA
buscoplotpy-0.0.2.dist-info/WHEEL
buscoplotpy-0.0.2.dist-info/top_level.txt
buscoplotpy-0.0.2.dist-info/RECORD
