Metadata-Version: 2.1
Name: buscoplotpy
Version: 0.0.2
Summary: A Python library for BUSCO data visualization.
Author-email: Lorenzo Arcioni <lorenzo.arcioni2000@gmail.com>
Project-URL: Homepage, https://github.com/lorenzo-arcioni/BUSCO-Plot-Py
Project-URL: Issues, https://github.com/lorenzo-arcioni/BUSCO-Plot-Py/issues
Classifier: Programming Language :: Python :: 3
Classifier: License :: OSI Approved :: MIT License
Classifier: Operating System :: OS Independent
Requires-Python: >=3.8
License-File: LICENSE
Requires-Dist: matplotlib
Requires-Dist: seaborn
Requires-Dist: pandas
